nbstudy/__about__.py
nbstudy/__init__.py
nbstudy/py.typed
nbstudy/cache/__init__.py
nbstudy/cli/__init__.py
nbstudy/cli/commands/__init__.py
nbstudy/cli/commands/cache.py
nbstudy/cli/commands/github.py
nbstudy/db/__init__.py
nbstudy/resources/.gitignore
nbstudy/resources/__init__.py
nbstudy/settings/__init__.py
nbstudy/settings/settings.py
nbstudy/workspace/__init__.py
nbstudy/workspace/workspace.py
nbstudy-0.0.1a2.dist-info/METADATA
nbstudy-0.0.1a2.dist-info/WHEEL
nbstudy-0.0.1a2.dist-info/entry_points.txt
nbstudy-0.0.1a2.dist-info/licenses/LICENSE.txt
nbstudy-0.0.1a2.dist-info/RECORD
