Metadata-Version: 2.1
Name: nbstudy
Version: 0.0.1a2
Summary: Tools for studying notebooks
Project-URL: Documentation, https://github.com/DylanLukes/nbstudy#readme
Project-URL: Issues, https://github.com/DylanLukes/nbstudy/issues
Project-URL: Source, https://github.com/DylanLukes/nbstudy
Author-email: Dylan Lukes <lukes.dylan@gmail.com>
License-Expression: BSD-3-Clause
License-File: LICENSE.txt
Classifier: Development Status :: 4 - Beta
Classifier: Programming Language :: Python
Classifier: Programming Language :: Python :: 3.12
Classifier: Programming Language :: Python :: Implementation :: CPython
Classifier: Programming Language :: Python :: Implementation :: PyPy
Requires-Python: >=3.12
Requires-Dist: click
Requires-Dist: gitpython
Requires-Dist: loguru
Requires-Dist: nbformat
Requires-Dist: pydantic
Requires-Dist: pydantic-settings
Requires-Dist: requests
